gos_asm/__init__.py
gos_asm/gos-asm.py
gos_asm/manager_assembler.py
gos_asm/algo/__init__.py
gos_asm/algo/default_configuration.py
gos_asm/algo/data_structures/__init__.py
gos_asm/algo/data_structures/assemblies.py
gos_asm/algo/data_structures/evolutionary_scenarios.py
gos_asm/algo/executable_containers/__init__.py
gos_asm/algo/executable_containers/wrappers.py
gos_asm/algo/shared/__init__.py
gos_asm/algo/shared/assembly_point.py
gos_asm/algo/shared/gos_asm_bg.py
gos_asm/algo/shared/gos_asm_logging.py
gos_asm/algo/tasks/__init__.py
gos_asm/algo/tasks/asm/__init__.py
gos_asm/algo/tasks/asm/connected_component.py
gos_asm/algo/tasks/asm/phylogeny.py
gos_asm/algo/tasks/asm/shared.py
gos_asm/algo/tasks/io/__init__.py
gos_asm/algo/tasks/io/input.py
gos_asm/algo/tasks/io/output.py
gos_asm/algo/tasks/mgra/__init__.py
gos_asm/algo/tasks/mgra/guidance_graph.py
gos_asm/examples/n_repeats/chimp/2000/blocks.txt
gos_asm/examples/n_repeats/chimp/2000/bridges.txt
gos_asm/examples/n_repeats/chimp/2000/config.py
gos_asm/examples/n_repeats/chimp/2000/__pycache__/config.cpython-36.pyc
gos_asm/examples/w_repeats/chimp/2000/blocks.txt
gos_asm/examples/w_repeats/chimp/2000/bridges.txt
gos_asm/examples/w_repeats/chimp/2000/config.py
gos_asm/examples/w_repeats/chimp/2000/config.pyc
gos_asm/examples/w_repeats/chimp/2000/__pycache__/config.cpython-36.pyc
gos_asm-0.10.data/scripts/gos-asm.py
gos_asm-0.10.dist-info/LICENSE
gos_asm-0.10.dist-info/METADATA
gos_asm-0.10.dist-info/WHEEL
gos_asm-0.10.dist-info/top_level.txt
gos_asm-0.10.dist-info/RECORD
